{"date": "2026-07-22", "by_sector": {"MOBILE": {"growth": [{"la": "Derby City", "delta": 3, "current": 93}, {"la": "Denbighshire", "delta": 2, "current": 27}, {"la": "Renfrewshire", "delta": 2, "current": 49}, {"la": "Sir Ddinbych", "delta": 2, "current": 27}, {"la": "Sandwell", "delta": 2, "current": 161}, {"la": "Gateshead", "delta": 1, "current": 96}, {"la": "Preston", "delta": 1, "current": 61}, {"la": "Medway", "delta": 1, "current": 97}, {"la": "Slough", "delta": 1, "current": 36}, {"la": "Test Valley", "delta": 1, "current": 105}], "reductions": [{"la": "Sir Benfro", "delta": -4, "current": 167}, {"la": "Pembrokeshire", "delta": -4, "current": 167}, {"la": "Cheshire East", "delta": -3, "current": 142}, {"la": "Hart", "delta": -1, "current": 41}, {"la": "Huntingdonshire", "delta": -1, "current": 70}, {"la": "Wyre", "delta": -1, "current": 37}, {"la": "Ribble Valley", "delta": -1, "current": 36}, {"la": "Ipswich", "delta": -1, "current": 61}, {"la": "St Helens", "delta": -1, "current": 94}, {"la": "North West Leicestershire", "delta": -1, "current": 75}]}, "RESTAURANT_CAFE": {"growth": [{"la": "Leeds", "delta": 2, "current": 1908}, {"la": "Sir y Fflint", "delta": 2, "current": 204}, {"la": "Northumberland", "delta": 2, "current": 693}, {"la": "Flintshire", "delta": 2, "current": 204}, {"la": "Conwy", "delta": 2, "current": 612}, {"la": "St Helens", "delta": 2, "current": 215}, {"la": "Cheshire East", "delta": 2, "current": 333}, {"la": "Swale", "delta": 2, "current": 250}, {"la": "Wandsworth", "delta": 1, "current": 1285}, {"la": "Portsmouth", "delta": 1, "current": 419}], "reductions": [{"la": "Derby City", "delta": -5, "current": 338}, {"la": "Ipswich", "delta": -3, "current": 272}, {"la": "North West Leicestershire", "delta": -2, "current": 335}, {"la": "Kingston-Upon-Thames", "delta": -2, "current": 438}, {"la": "Colchester", "delta": -1, "current": 510}, {"la": "Mid Devon", "delta": -1, "current": 147}, {"la": "Wyre", "delta": -1, "current": 205}, {"la": "Brentwood", "delta": -1, "current": 132}, {"la": "Solihull", "delta": -1, "current": 375}, {"la": "Salford", "delta": -1, "current": 442}]}, "PUB_BAR": {"growth": [{"la": "Cheshire East", "delta": 3, "current": 303}, {"la": "Denbighshire", "delta": 1, "current": 57}, {"la": "Mid Devon", "delta": 1, "current": 89}, {"la": "Sir y Fflint", "delta": 1, "current": 148}, {"la": "Northumberland", "delta": 1, "current": 436}, {"la": "Harlow", "delta": 1, "current": 52}, {"la": "Flintshire", "delta": 1, "current": 148}, {"la": "Calderdale", "delta": 1, "current": 255}, {"la": "North Devon", "delta": 1, "current": 117}, {"la": "Sir Ddinbych", "delta": 1, "current": 57}], "reductions": [{"la": "Slough", "delta": -2, "current": 25}, {"la": "Norwich City", "delta": -1, "current": 158}, {"la": "Middlesbrough", "delta": -1, "current": 82}, {"la": "St Helens", "delta": -1, "current": 153}, {"la": "Pendle", "delta": -1, "current": 75}, {"la": "Kirklees", "delta": -1, "current": 474}, {"la": "Vale of White Horse", "delta": -1, "current": 110}, {"la": "Sir Benfro", "delta": -1, "current": 177}, {"la": "Pembrokeshire", "delta": -1, "current": 177}, {"la": "Test Valley", "delta": -1, "current": 109}]}, "TAKEAWAY": {"growth": [{"la": "Renfrewshire", "delta": 5, "current": 211}, {"la": "Derby City", "delta": 4, "current": 304}, {"la": "Calderdale", "delta": 2, "current": 252}, {"la": "Conwy", "delta": 2, "current": 282}, {"la": "Kirklees", "delta": 2, "current": 577}, {"la": "Sandwell", "delta": 2, "current": 425}, {"la": "Wandsworth", "delta": 1, "current": 183}, {"la": "Denbighshire", "delta": 1, "current": 123}, {"la": "Colchester", "delta": 1, "current": 141}, {"la": "Epping Forest", "delta": 1, "current": 43}], "reductions": [{"la": "Leeds", "delta": -2, "current": 802}, {"la": "Clackmannanshire", "delta": -2, "current": 53}, {"la": "Salford", "delta": -2, "current": 341}, {"la": "St Helens", "delta": -2, "current": 184}, {"la": "Bath and North East Somerset", "delta": -1, "current": 121}, {"la": "Harrow", "delta": -1, "current": 200}, {"la": "Kingston-Upon-Thames", "delta": -1, "current": 149}]}, "HOTEL": {"growth": [{"la": "Conwy", "delta": 2, "current": 446}, {"la": "Bath and North East Somerset", "delta": 1, "current": 65}], "reductions": [{"la": "Sir Benfro", "delta": -1, "current": 179}, {"la": "Pembrokeshire", "delta": -1, "current": 179}]}}}