{"date": "2026-06-19", "by_sector": {"MOBILE": {"growth": [{"la": "Croydon", "delta": 9, "current": 164}, {"la": "Runnymede", "delta": 3, "current": 46}, {"la": "Somerset", "delta": 3, "current": 391}, {"la": "Mid Ulster", "delta": 2, "current": 77}, {"la": "New Forest", "delta": 2, "current": 67}, {"la": "South Staffordshire", "delta": 2, "current": 46}, {"la": "Lisburn and Castlereagh City", "delta": 1, "current": 61}, {"la": "Tonbridge and Malling", "delta": 1, "current": 78}, {"la": "Lincoln City", "delta": 1, "current": 47}, {"la": "Shropshire", "delta": 1, "current": 189}], "reductions": [{"la": "North Tyneside", "delta": -2, "current": 65}, {"la": "Antrim and Newtownabbey", "delta": -2, "current": 67}, {"la": "West Oxfordshire", "delta": -1, "current": 100}, {"la": "Hart", "delta": -1, "current": 43}, {"la": "Trafford", "delta": -1, "current": 87}, {"la": "Welwyn Hatfield", "delta": -1, "current": 36}, {"la": "South Kesteven", "delta": -1, "current": 51}, {"la": "Argyll and Bute", "delta": -1, "current": 63}, {"la": "Kensington and Chelsea", "delta": -1, "current": 21}, {"la": "Salford", "delta": -1, "current": 86}]}, "RESTAURANT_CAFE": {"growth": [{"la": "Antrim and Newtownabbey", "delta": 3, "current": 186}, {"la": "Glasgow City", "delta": 3, "current": 2146}, {"la": "Rochdale", "delta": 2, "current": 240}, {"la": "Runnymede", "delta": 2, "current": 281}, {"la": "Chichester", "delta": 2, "current": 273}, {"la": "North Norfolk", "delta": 1, "current": 308}, {"la": "Torridge", "delta": 1, "current": 113}, {"la": "Trafford", "delta": 1, "current": 551}, {"la": "Tonbridge and Malling", "delta": 1, "current": 176}, {"la": "Rushcliffe", "delta": 1, "current": 229}], "reductions": [{"la": "Kensington and Chelsea", "delta": -11, "current": 972}, {"la": "Cotswold", "delta": -4, "current": 295}, {"la": "Somerset", "delta": -4, "current": 1113}, {"la": "Fife", "delta": -3, "current": 701}, {"la": "North Tyneside", "delta": -2, "current": 294}, {"la": "Newcastle-Under-Lyme", "delta": -2, "current": 86}, {"la": "Leeds", "delta": -2, "current": 1909}, {"la": "Hounslow", "delta": -1, "current": 591}, {"la": "Knowsley", "delta": -1, "current": 149}, {"la": "Reading", "delta": -1, "current": 341}]}, "PUB_BAR": {"growth": [{"la": "Glasgow City", "delta": 1, "current": 357}, {"la": "Rushcliffe", "delta": 1, "current": 71}, {"la": "South Tyneside", "delta": 1, "current": 119}], "reductions": [{"la": "North Tyneside", "delta": -1, "current": 154}, {"la": "Cotswold", "delta": -1, "current": 138}, {"la": "Tonbridge and Malling", "delta": -1, "current": 109}, {"la": "Runnymede", "delta": -1, "current": 58}, {"la": "Somerset", "delta": -1, "current": 610}, {"la": "Kensington and Chelsea", "delta": -1, "current": 99}, {"la": "North Hertfordshire", "delta": -1, "current": 129}]}, "TAKEAWAY": {"growth": [{"la": "Welwyn Hatfield", "delta": 2, "current": 60}, {"la": "Hounslow", "delta": 1, "current": 240}, {"la": "North Tyneside", "delta": 1, "current": 192}, {"la": "Mid Ulster", "delta": 1, "current": 132}, {"la": "Antrim and Newtownabbey", "delta": 1, "current": 102}, {"la": "Glasgow City", "delta": 1, "current": 1104}, {"la": "Newcastle-Under-Lyme", "delta": 1, "current": 120}, {"la": "South Staffordshire", "delta": 1, "current": 59}, {"la": "Lincoln City", "delta": 1, "current": 124}], "reductions": [{"la": "Tonbridge and Malling", "delta": -3, "current": 82}, {"la": "West Dunbartonshire", "delta": -2, "current": 102}, {"la": "Rushcliffe", "delta": -1, "current": 86}, {"la": "Tunbridge Wells", "delta": -1, "current": 66}, {"la": "Shropshire", "delta": -1, "current": 226}]}, "HOTEL": {"growth": [{"la": "Lincoln City", "delta": 1, "current": 24}, {"la": "Croydon", "delta": 1, "current": 31}], "reductions": [{"la": "Torridge", "delta": -1, "current": 38}, {"la": "North Tyneside", "delta": -1, "current": 14}, {"la": "Cotswold", "delta": -1, "current": 70}, {"la": "South Tyneside", "delta": -1, "current": 13}, {"la": "Somerset", "delta": -1, "current": 219}, {"la": "Kensington and Chelsea", "delta": -1, "current": 68}]}}}