{"date": "2026-03-28", "by_sector": {"MOBILE": {"growth": [{"la": "Walsall", "delta": 9, "current": 209}, {"la": "Herefordshire", "delta": 4, "current": 145}, {"la": "Staffordshire Moorlands", "delta": 3, "current": 77}, {"la": "Wakefield", "delta": 2, "current": 156}, {"la": "Burnley", "delta": 2, "current": 26}, {"la": "Mid Sussex", "delta": 2, "current": 81}, {"la": "Liverpool", "delta": 2, "current": 155}, {"la": "Bolsover", "delta": 1, "current": 104}, {"la": "Moray", "delta": 1, "current": 50}, {"la": "Falkirk", "delta": 1, "current": 74}], "reductions": [{"la": "Sandwell", "delta": -5, "current": 144}, {"la": "Broadland", "delta": -3, "current": 68}, {"la": "Amber Valley", "delta": -3, "current": 117}, {"la": "Brighton and Hove", "delta": -2, "current": 71}, {"la": "Torfaen", "delta": -2, "current": 82}, {"la": "Bolton", "delta": -2, "current": 168}, {"la": "Harrow", "delta": -1, "current": 51}, {"la": "Torbay", "delta": -1, "current": 96}, {"la": "Northumberland", "delta": -1, "current": 169}, {"la": "Mid and East Antrim", "delta": -1, "current": 67}]}, "RESTAURANT_CAFE": {"growth": [{"la": "Midlothian", "delta": 6, "current": 184}, {"la": "Cornwall", "delta": 6, "current": 1651}, {"la": "Torbay", "delta": 3, "current": 286}, {"la": "Epsom and Ewell", "delta": 3, "current": 201}, {"la": "Tonbridge and Malling", "delta": 3, "current": 175}, {"la": "South Ayrshire", "delta": 3, "current": 243}, {"la": "Leicester City", "delta": 3, "current": 740}, {"la": "Walsall", "delta": 3, "current": 363}, {"la": "Staffordshire Moorlands", "delta": 2, "current": 167}, {"la": "Torfaen", "delta": 2, "current": 220}], "reductions": [{"la": "Sandwell", "delta": -6, "current": 453}, {"la": "Brighton and Hove", "delta": -5, "current": 999}, {"la": "Mid Sussex", "delta": -4, "current": 289}, {"la": "Harrow", "delta": -3, "current": 487}, {"la": "Wakefield", "delta": -3, "current": 551}, {"la": "Charnwood", "delta": -3, "current": 277}, {"la": "Moray", "delta": -2, "current": 167}, {"la": "Thurrock", "delta": -2, "current": 234}, {"la": "Shropshire", "delta": -2, "current": 722}, {"la": "Medway", "delta": -1, "current": 303}]}, "PUB_BAR": {"growth": [{"la": "Shropshire", "delta": 5, "current": 413}, {"la": "Cornwall", "delta": 4, "current": 545}, {"la": "Derby City", "delta": 2, "current": 204}, {"la": "Staffordshire Moorlands", "delta": 1, "current": 115}, {"la": "Brighton and Hove", "delta": 1, "current": 341}, {"la": "Sandwell", "delta": 1, "current": 115}, {"la": "Cambridge City", "delta": 1, "current": 97}, {"la": "High Peak", "delta": 1, "current": 125}, {"la": "Mid Sussex", "delta": 1, "current": 116}, {"la": "Liverpool", "delta": 1, "current": 519}], "reductions": [{"la": "Wakefield", "delta": -3, "current": 325}, {"la": "Northumberland", "delta": -3, "current": 431}, {"la": "Moray", "delta": -2, "current": 56}, {"la": "Barnsley", "delta": -2, "current": 289}, {"la": "Edinburgh (City of)", "delta": -2, "current": 503}, {"la": "Torfaen", "delta": -2, "current": 180}, {"la": "North Yorkshire", "delta": -1, "current": 774}, {"la": "Thurrock", "delta": -1, "current": 54}, {"la": "Charnwood", "delta": -1, "current": 181}, {"la": "Herefordshire", "delta": -1, "current": 208}]}, "TAKEAWAY": {"growth": [{"la": "Liverpool", "delta": 6, "current": 757}, {"la": "Cornwall", "delta": 5, "current": 440}, {"la": "Burnley", "delta": 3, "current": 145}, {"la": "Derby City", "delta": 3, "current": 298}, {"la": "St Helens", "delta": 3, "current": 190}, {"la": "Swansea", "delta": 2, "current": 258}, {"la": "Westminster", "delta": 2, "current": 274}, {"la": "Fareham", "delta": 2, "current": 43}, {"la": "Exeter City", "delta": 2, "current": 82}, {"la": "Abertawe", "delta": 2, "current": 258}], "reductions": [{"la": "Sandwell", "delta": -6, "current": 415}, {"la": "Wakefield", "delta": -5, "current": 460}, {"la": "Thurrock", "delta": -2, "current": 148}, {"la": "Midlothian", "delta": -2, "current": 48}, {"la": "Charnwood", "delta": -2, "current": 140}, {"la": "Surrey Heath", "delta": -2, "current": 102}, {"la": "Leicester City", "delta": -2, "current": 549}, {"la": "Harrow", "delta": -1, "current": 211}, {"la": "Staffordshire Moorlands", "delta": -1, "current": 81}, {"la": "Moray", "delta": -1, "current": 105}]}, "HOTEL": {"growth": [{"la": "Cornwall", "delta": 1, "current": 212}], "reductions": [{"la": "Northumberland", "delta": -8, "current": 189}, {"la": "Brighton and Hove", "delta": -3, "current": 62}, {"la": "Torbay", "delta": -2, "current": 230}, {"la": "Broadland", "delta": -1, "current": 7}, {"la": "Newcastle-Under-Lyme", "delta": -1, "current": 8}, {"la": "Shetland Islands", "delta": -1, "current": 30}]}}}