{"date": "2026-05-15", "by_sector": {"MOBILE": {"growth": [{"la": "Gwynedd", "delta": 8, "current": 238}, {"la": "Maidstone", "delta": 5, "current": 90}, {"la": "Croydon", "delta": 5, "current": 154}, {"la": "Sefton", "delta": 4, "current": 79}, {"la": "Canterbury City", "delta": 4, "current": 106}, {"la": "Rochdale", "delta": 3, "current": 65}, {"la": "Leeds", "delta": 3, "current": 342}, {"la": "North Somerset", "delta": 3, "current": 94}, {"la": "Sunderland", "delta": 3, "current": 150}, {"la": "Enfield", "delta": 2, "current": 100}], "reductions": [{"la": "Gravesham", "delta": -2, "current": 44}, {"la": "Stoke-On-Trent", "delta": -2, "current": 47}, {"la": "Newham", "delta": -2, "current": 123}, {"la": "Lichfield", "delta": -1, "current": 58}, {"la": "North Norfolk", "delta": -1, "current": 125}, {"la": "Brent", "delta": -1, "current": 78}, {"la": "Pendle", "delta": -1, "current": 44}, {"la": "South Ayrshire", "delta": -1, "current": 15}, {"la": "Birmingham", "delta": -1, "current": 389}, {"la": "Redditch", "delta": -1, "current": 47}]}, "RESTAURANT_CAFE": {"growth": [{"la": "Anglesey", "delta": 18, "current": 164}, {"la": "Ynys Môn", "delta": 18, "current": 164}, {"la": "Brent", "delta": 4, "current": 558}, {"la": "Gwynedd", "delta": 4, "current": 1036}, {"la": "Maidstone", "delta": 4, "current": 283}, {"la": "Rochdale", "delta": 3, "current": 235}, {"la": "Swindon", "delta": 3, "current": 310}, {"la": "Trafford", "delta": 3, "current": 554}, {"la": "Leeds", "delta": 2, "current": 1912}, {"la": "Tamworth", "delta": 2, "current": 83}], "reductions": [{"la": "Enfield", "delta": -4, "current": 567}, {"la": "South Lanarkshire", "delta": -4, "current": 742}, {"la": "Birmingham", "delta": -3, "current": 2527}, {"la": "East Renfrewshire", "delta": -2, "current": 105}, {"la": "Wychavon", "delta": -2, "current": 190}, {"la": "Croydon", "delta": -2, "current": 597}, {"la": "Stoke-On-Trent", "delta": -2, "current": 348}, {"la": "Newham", "delta": -2, "current": 638}, {"la": "Lichfield", "delta": -1, "current": 255}, {"la": "Forest of Dean", "delta": -1, "current": 241}]}, "PUB_BAR": {"growth": [{"la": "Gwynedd", "delta": 4, "current": 326}, {"la": "Maidstone", "delta": 3, "current": 130}, {"la": "Wiltshire", "delta": 3, "current": 519}, {"la": "Rochdale", "delta": 1, "current": 179}, {"la": "Forest of Dean", "delta": 1, "current": 69}, {"la": "West Oxfordshire", "delta": 1, "current": 108}, {"la": "North Norfolk", "delta": 1, "current": 133}, {"la": "Inverclyde", "delta": 1, "current": 67}, {"la": "Sefton", "delta": 1, "current": 256}, {"la": "East Devon", "delta": 1, "current": 154}], "reductions": [{"la": "Birmingham", "delta": -3, "current": 481}, {"la": "Wolverhampton", "delta": -2, "current": 209}, {"la": "Leeds", "delta": -1, "current": 609}, {"la": "Lichfield", "delta": -1, "current": 128}, {"la": "Brent", "delta": -1, "current": 81}, {"la": "Croydon", "delta": -1, "current": 75}, {"la": "Canterbury City", "delta": -1, "current": 170}, {"la": "Stoke-On-Trent", "delta": -1, "current": 208}, {"la": "Newark and Sherwood", "delta": -1, "current": 133}]}, "TAKEAWAY": {"growth": [{"la": "Stroud", "delta": 5, "current": 145}, {"la": "Gwynedd", "delta": 4, "current": 274}, {"la": "West Lindsey", "delta": 3, "current": 72}, {"la": "Rochdale", "delta": 2, "current": 324}, {"la": "Lambeth", "delta": 2, "current": 415}, {"la": "Trafford", "delta": 2, "current": 248}, {"la": "Canterbury City", "delta": 2, "current": 126}, {"la": "Waverley", "delta": 1, "current": 58}, {"la": "Swindon", "delta": 1, "current": 138}, {"la": "Milton Keynes", "delta": 1, "current": 280}], "reductions": [{"la": "Newham", "delta": -4, "current": 387}, {"la": "Croydon", "delta": -3, "current": 435}, {"la": "Birmingham", "delta": -3, "current": 1032}, {"la": "South Lanarkshire", "delta": -2, "current": 285}, {"la": "Maidstone", "delta": -2, "current": 102}, {"la": "Inverclyde", "delta": -2, "current": 80}, {"la": "Wyre Forest", "delta": -2, "current": 87}, {"la": "South Ayrshire", "delta": -2, "current": 115}, {"la": "Wolverhampton", "delta": -2, "current": 280}, {"la": "Leeds", "delta": -1, "current": 804}]}, "HOTEL": {"growth": [{"la": "Gwynedd", "delta": 4, "current": 362}, {"la": "Somerset", "delta": 1, "current": 202}, {"la": "Wyre Forest", "delta": 1, "current": 12}], "reductions": [{"la": "Anglesey", "delta": -14, "current": 24}, {"la": "Ynys Môn", "delta": -14, "current": 24}, {"la": "Trafford", "delta": -1, "current": 20}, {"la": "North Somerset", "delta": -1, "current": 39}, {"la": "South Ayrshire", "delta": -1, "current": 51}, {"la": "Birmingham", "delta": -1, "current": 96}]}}}